dxtb/__init__.py
dxtb/__main__.py
dxtb/__version__.py
dxtb/calculators.py
dxtb/config.py
dxtb/labels.py
dxtb/py.typed
dxtb/typing.py
dxtb/_src/__init__.py
dxtb/_src/basis/__init__.py
dxtb/_src/basis/bas.py
dxtb/_src/basis/indexhelper.py
dxtb/_src/basis/ortho.py
dxtb/_src/basis/slater.py
dxtb/_src/basis/sto-ng/sto-1g.npy
dxtb/_src/basis/sto-ng/sto-2g.npy
dxtb/_src/basis/sto-ng/sto-3g.npy
dxtb/_src/basis/sto-ng/sto-4g.npy
dxtb/_src/basis/sto-ng/sto-5g.npy
dxtb/_src/basis/sto-ng/sto-6g.npy
dxtb/_src/calculators/__init__.py
dxtb/_src/calculators/base.py
dxtb/_src/calculators/gfn1.py
dxtb/_src/calculators/gfn2.py
dxtb/_src/calculators/result.py
dxtb/_src/calculators/config/__init__.py
dxtb/_src/calculators/config/cache.py
dxtb/_src/calculators/config/integral.py
dxtb/_src/calculators/config/main.py
dxtb/_src/calculators/config/scf.py
dxtb/_src/calculators/properties/__init__.py
dxtb/_src/calculators/properties/moments/__init__.py
dxtb/_src/calculators/properties/moments/dip.py
dxtb/_src/calculators/properties/moments/quad.py
dxtb/_src/calculators/properties/vibration/__init__.py
dxtb/_src/calculators/properties/vibration/analysis.py
dxtb/_src/calculators/properties/vibration/ir.py
dxtb/_src/calculators/properties/vibration/raman.py
dxtb/_src/calculators/properties/vibration/result.py
dxtb/_src/calculators/types/__init__.py
dxtb/_src/calculators/types/abc.py
dxtb/_src/calculators/types/analytical.py
dxtb/_src/calculators/types/autograd.py
dxtb/_src/calculators/types/base.py
dxtb/_src/calculators/types/decorators.py
dxtb/_src/calculators/types/energy.py
dxtb/_src/calculators/types/numerical.py
dxtb/_src/cli/__init__.py
dxtb/_src/cli/argparser.py
dxtb/_src/cli/driver.py
dxtb/_src/cli/entrypoint.py
dxtb/_src/components/__init__.py
dxtb/_src/components/base.py
dxtb/_src/components/list.py
dxtb/_src/components/utils.py
dxtb/_src/components/classicals/__init__.py
dxtb/_src/components/classicals/base.py
dxtb/_src/components/classicals/list.py
dxtb-0.3.0.dist-info/licenses/LICENSE
dxtb-0.3.0.dist-info/METADATA
dxtb-0.3.0.dist-info/WHEEL
dxtb-0.3.0.dist-info/entry_points.txt
dxtb-0.3.0.dist-info/top_level.txt
dxtb-0.3.0.dist-info/RECORD
