Metadata-Version: 2.4
Name: dxtb
Version: 0.3.0
Summary: Fully Differentiable Approach to Extended Tight Binding
Home-page: https://github.com/grimme-lab/dxtb
Author: "Sebastian Ehlert, Marvin Friede, Christian Hölzer"
License: Apache-2.0
Project-URL: Documentation, https://github.com/grimme-lab/dxtb
Project-URL: Tracker, https://github.com/grimme-lab/dxtb/issues
Project-URL: Source Code, https://github.com/grimme-lab/dxtb
Keywords: pytorch,autograd,tight-binding,xtb,computational chemistry,quantum chemistry,machine learning
Classifier: Intended Audience :: Developers
Classifier: Intended Audience :: Science/Research
Classifier: Natural Language :: English
Classifier: Operating System :: MacOS
Classifier: Operating System :: Microsoft :: Windows
Classifier: Operating System :: POSIX
Classifier: Operating System :: POSIX :: Linux
Classifier: Programming Language :: Python :: 3
Classifier: Programming Language :: Python :: 3 :: Only
Classifier: Programming Language :: Python :: 3.8
Classifier: Programming Language :: Python :: 3.9
Classifier: Programming Language :: Python :: 3.10
Classifier: Programming Language :: Python :: 3.11
Classifier: Programming Language :: Python :: 3.12
Classifier: Programming Language :: Python :: Implementation :: CPython
Classifier: Topic :: Scientific/Engineering :: Chemistry
Classifier: Typing :: Typed
Requires-Python: <3.13,>=3.8
License-File: LICENSE
Requires-Dist: numpy<2
Requires-Dist: pydantic>=2.0.0
Requires-Dist: scipy
Requires-Dist: tad-dftd3==0.5.0
Requires-Dist: tad-dftd4==0.7.0
Requires-Dist: tad-mctc==0.5.3
Requires-Dist: tad-multicharge==0.3.3
Requires-Dist: tomli
Requires-Dist: tomli-w
Requires-Dist: torch<3,>=1.11.0
Requires-Dist: typing-extensions
Provides-Extra: dev
Requires-Dist: black; extra == "dev"
Requires-Dist: covdefaults; extra == "dev"
Requires-Dist: mypy; extra == "dev"
Requires-Dist: pre-commit; extra == "dev"
Requires-Dist: pylint; extra == "dev"
Requires-Dist: pyscf; extra == "dev"
Requires-Dist: pytest; extra == "dev"
Requires-Dist: pytest-cov; extra == "dev"
Requires-Dist: pytest-random-order; extra == "dev"
Requires-Dist: pytest-xdist; extra == "dev"
Requires-Dist: pyyaml; extra == "dev"
Requires-Dist: tox; extra == "dev"
Provides-Extra: libcint
Requires-Dist: tad-libcint>=0.1.2; extra == "libcint"
Provides-Extra: pyscf
Requires-Dist: pyscf; extra == "pyscf"
Provides-Extra: tox
Requires-Dist: covdefaults; extra == "tox"
Requires-Dist: pytest; extra == "tox"
Requires-Dist: pytest-cov; extra == "tox"
Requires-Dist: pytest-random-order; extra == "tox"
Requires-Dist: pytest-xdist; extra == "tox"
Requires-Dist: pyyaml; extra == "tox"
Dynamic: license-file
